{
   "COLOR" : {
      "CORIOLIS" : "#0055FF",
      "MEDS" : "#FF0000",
      "CSIO" : "#00AAFF",
      "GTS" : "#52FFA5",
      "NMDIS" : "#A50000",
      "CSIRO" : "#00FFFF",
      "BODC" : "#0000FF",
      "KORDI" : "#FF5500",
      "INCOIS" : "#A5FF52",
      "KMA" : "#FFAA00",
      "JMA" : "#FFFF00",
      "AOML" : "#0000A5"
   },
   "DELAYED" : {
      "GDAC" : {
         "KIOST" : [
            15979
         ],
         "AOML" : [
            1549494
         ],
         "CSIRO" : [
            230778
         ],
         "KMA" : [
            35475
         ],
         "JMA" : [
            229396
         ],
         "NMDIS" : [
            2388
         ],
         "INCOIS" : [
            76567
         ],
         "CORIOLIS" : [
            461789
         ],
         "MEDS" : [
            58064
         ],
         "CSIO" : [
            75622
         ],
         "BODC" : [
            104000
         ]
      },
      "TOTAL" : 2839552
   },
   "DATE" : "14/04/2026",
   "ALL" : {
      "TOTAL" : 20124,
      "GDAC" : {
         "CSIRO" : [
            1241
         ],
         "AOML" : [
            9511
         ],
         "KIOST" : [
            130
         ],
         "NMDIS" : [
            19
         ],
         "JMA" : [
            2004
         ],
         "KMA" : [
            263
         ],
         "INCOIS" : [
            597
         ],
         "BODC" : [
            938
         ],
         "CSIO" : [
            586
         ],
         "CORIOLIS" : [
            4111
         ],
         "MEDS" : [
            724
         ]
      }
   },
   "ACTIVE" : {
      "GDAC" : {
         "CORIOLIS" : [
            848
         ],
         "MEDS" : [
            201
         ],
         "CSIO" : [
            79
         ],
         "BODC" : [
            156
         ],
         "INCOIS" : [
            120
         ],
         "JMA" : [
            155
         ],
         "KIOST" : [
            19
         ],
         "CSIRO" : [
            295
         ],
         "AOML" : [
            2473
         ]
      },
      "TOTAL" : 4346
   }
}

